dubna_parser/.git/COMMIT_EDITMSG
dubna_parser/.git/config
dubna_parser/.git/description
dubna_parser/.git/HEAD
dubna_parser/.git/hooks/applypatch-msg.sample
dubna_parser/.git/hooks/commit-msg.sample
dubna_parser/.git/hooks/fsmonitor-watchman.sample
dubna_parser/.git/hooks/post-update.sample
dubna_parser/.git/hooks/pre-applypatch.sample
dubna_parser/.git/hooks/pre-commit.sample
dubna_parser/.git/hooks/pre-merge-commit.sample
dubna_parser/.git/hooks/pre-push.sample
dubna_parser/.git/hooks/pre-rebase.sample
dubna_parser/.git/hooks/pre-receive.sample
dubna_parser/.git/hooks/prepare-commit-msg.sample
dubna_parser/.git/hooks/push-to-checkout.sample
dubna_parser/.git/hooks/sendemail-validate.sample
dubna_parser/.git/hooks/update.sample
dubna_parser/.git/index
dubna_parser/.git/info/exclude
dubna_parser/.git/logs/HEAD
dubna_parser/.git/logs/refs/heads/master
dubna_parser/.git/logs/refs/remotes/origin/master
dubna_parser/.git/objects/29/d7d61ebf7a41c178ffcf59a4d2875f6a043b6d
dubna_parser/.git/objects/66/911a6a3fcac27b4eb54c67943e6c4b321f8134
dubna_parser/.git/objects/7f/f3225401d1f94cde026725f290acb231276a33
dubna_parser/.git/objects/8d/e7e1b6d88506678329e4c07283b54b56796343
dubna_parser/.git/objects/a7/adab622932865b7f988b0b366edec2f4f68de3
dubna_parser/.git/objects/e1/44ec1638a1cf41740aa06aa168ca5795ac156e
dubna_parser/.git/objects/e6/9de29bb2d1d6434b8b29ae775ad8c2e48c5391
dubna_parser/.git/objects/ea/6d745a7a081b53204c491954a8297effc6d5eb
dubna_parser/.git/objects/f3/1a7477b39ce30d2c1e66545d299f49a238519a
dubna_parser/.git/objects/f6/30376b6d4ef45d89997c6807518dfaa360bec6
dubna_parser/.git/refs/heads/master
dubna_parser/.git/refs/remotes/origin/master
dubna_parser/__init__.py
dubna_parser/downloader.py
dubna_parser/help_functions.py
dubna_parser/models.py
dubna_parser/parser.py
dubna_schedule_parser-1.0.2.dist-info/METADATA
dubna_schedule_parser-1.0.2.dist-info/WHEEL
dubna_schedule_parser-1.0.2.dist-info/RECORD
