Metadata-Version: 2.1
Name: dubna-schedule-parser
Version: 1.0.2
Summary: Download and parse excel files from schedules of University Dubna
Author: Skelesheit
Author-email: skelesheit@gmail.com
Requires-Python: >=3.8,<4.0
Classifier: Programming Language :: Python :: 3
Classifier: Programming Language :: Python :: 3.8
Classifier: Programming Language :: Python :: 3.9
Classifier: Programming Language :: Python :: 3.10
Classifier: Programming Language :: Python :: 3.11
Classifier: Programming Language :: Python :: 3.12
Requires-Dist: gdown (>=5.2.0,<6.0.0)
Requires-Dist: openpyxl (>=3.1.5,<4.0.0)
Requires-Dist: pydantic (>=2,<3)
